pydentity_db_sqlalchemy/__init__.py
pydentity_db_sqlalchemy/fields.py
pydentity_db_sqlalchemy/models/__init__.py
pydentity_db_sqlalchemy/models/abstract.py
pydentity_db_sqlalchemy/models/base.py
pydentity_db_sqlalchemy/stores/__init__.py
pydentity_db_sqlalchemy/stores/role_store.py
pydentity_db_sqlalchemy/stores/user_store.py
pydentity_db_sqlalchemy-0.1.3.dist-info/LICENSE
pydentity_db_sqlalchemy-0.1.3.dist-info/METADATA
pydentity_db_sqlalchemy-0.1.3.dist-info/WHEEL
pydentity_db_sqlalchemy-0.1.3.dist-info/RECORD
